psychopy_labhackers/__init__.py
psychopy_labhackers/labhackers.py
psychopy_labhackers-0.0.1.dist-info/LICENSE
psychopy_labhackers-0.0.1.dist-info/METADATA
psychopy_labhackers-0.0.1.dist-info/WHEEL
psychopy_labhackers-0.0.1.dist-info/top_level.txt
psychopy_labhackers-0.0.1.dist-info/RECORD
