Metadata-Version: 2.1
Name: psychopy-labhackers
Version: 0.0.1
Summary: Extension package for adding support for devices by LabHackers Research Equipment to PsychoPy.
Author-email: Sol Simpson <sol@labhackers.com>, Jon Peirce <jon@opensceincetools.org>, Matthew Cutone <mcutone@opensceincetools.org>
License: GNU General Public License v3 (GPLv3)
Project-URL: homepage, https://github.com/mdcutone/psychopy-labhackers
Project-URL: changelog, https://github.com/mdcutone/psychopy-labhackers/blob/main/CHANGELOG.txt
Project-URL: documentation, https://pages.github.com/psychopy/psychopy-labhackers
Project-URL: repository, https://github.com/psychopy/psychopy-labhackers
Classifier: License :: OSI Approved :: GNU General Public License v3 (GPLv3)
Classifier: Programming Language :: Python :: 3
Classifier: Programming Language :: Python :: 3 :: Only
Classifier: Programming Language :: Python :: 3.7
Classifier: Programming Language :: Python :: 3.8
Classifier: Programming Language :: Python :: 3.9
Classifier: Programming Language :: Python :: 3.10
Classifier: Programming Language :: Python :: 3.11
Classifier: Programming Language :: Python :: Implementation :: CPython
Requires-Python: >=3.7
License-File: LICENSE
Requires-Dist: pyserial
